{
  "parsed_at": "2026-02-11T05:42:05.159591+00:00",
  "total_messages_scanned": 8217,
  "total_chats_scanned": 790,
  "relevant_vacancies": [],
  "irrelevant_messages": [
    {
      "channel": "Витязь. Охотник (Письмоносец)",
      "message_id": 2906,
      "rejection_reason": "Рекламный/промо контент",
      "score": 0
    },
    {
      "channel": "Фриланс | Твой помощник",
      "message_id": 30171103,
      "rejection_reason": "Специализация не определена (даже через ключевые слова)",
      "score": 0
    },
    {
      "channel": "Фриланс | Твой помощник",
      "message_id": 30171095,
      "rejection_reason": "Рекламный/промо контент",
      "score": 0
    },
    {
      "channel": "Фриланс | Твой помощник",
      "message_id": 30171074,
      "rejection_reason": "Нет сигналов лида (Вакансия/Контекст/Ключевики)",
      "score": 0
    },
    {
      "channel": "Фриланс чат | Вакансии",
      "message_id": 13334670,
      "rejection_reason": "Рекламный/промо контент",
      "score": 0
    },
    {
      "channel": "Фриланс Форекс и Удаленная Работа Вакансии",
      "message_id": 28751489,
      "rejection_reason": "Нет сигналов лида (Вакансия/Контекст/Ключевики)",
      "score": 0
    },
    {
      "channel": "Фриланс Форекс и Удаленная Работа Вакансии",
      "message_id": 28751440,
      "rejection_reason": "Рекламный/промо контент",
      "score": 0
    },
    {
      "channel": "Чат Фриланс | Вакансии | Удаленка",
      "message_id": 16589795,
      "rejection_reason": "Нет сигналов лида (Вакансия/Контекст/Ключевики)",
      "score": 0
    },
    {
      "channel": "ПОИСК ФРИЛАНСЕРОВ | ЧАТ",
      "message_id": 4270916,
      "rejection_reason": "Рекламный/промо контент",
      "score": 0
    },
    {
      "channel": "ПОИСК ФРИЛАНСЕРОВ | ЧАТ",
      "message_id": 4270907,
      "rejection_reason": "Рекламный/промо контент",
      "score": 0
    },
    {
      "channel": "ЧАТ ПОИСК РАБОТЫ ВАКАНСИИ ФРИЛАНС УДАЛЕНКА",
      "message_id": 19210958,
      "rejection_reason": "Нет сигналов лида (Вакансия/Контекст/Ключевики)",
      "score": 0
    },
    {
      "channel": "ЧАТ ПОИСК РАБОТЫ ВАКАНСИИ ФРИЛАНС УДАЛЕНКА",
      "message_id": 19210941,
      "rejection_reason": "Нет сигналов лида (Вакансия/Контекст/Ключевики)",
      "score": 0
    },
    {
      "channel": "ФРИЛАНС ЧАТИК🖤",
      "message_id": 13074539,
      "rejection_reason": "Рекламный/промо контент",
      "score": 0
    },
    {
      "channel": "ФРИЛАНС ЧАТ|ВАКАНСИИ|РЕЗЮМЕ|РАБОТА|УСЛУГИ",
      "message_id": 5546435,
      "rejection_reason": "Нет сигналов лида (Вакансия/Контекст/Ключевики)",
      "score": 0
    },
    {
      "channel": "ФРИЛАНС ЧАТ|ВАКАНСИИ|РЕЗЮМЕ|РАБОТА|УСЛУГИ",
      "message_id": 5546395,
      "rejection_reason": "Нет сигналов лида (Вакансия/Контекст/Ключевики)",
      "score": 0
    },
    {
      "channel": "Фриланс чат | Вакансии",
      "message_id": 16864598,
      "rejection_reason": "Нет сигналов лида (Вакансия/Контекст/Ключевики)",
      "score": 0
    },
    {
      "channel": "Фриланс чат | Вакансии",
      "message_id": 16864596,
      "rejection_reason": "Рекламный/промо контент",
      "score": 0
    },
    {
      "channel": "Фриланс чат | Вакансии",
      "message_id": 16864590,
      "rejection_reason": "Рекламный/промо контент",
      "score": 0
    },
    {
      "channel": "Фриланс чат | Вакансии",
      "message_id": 16864589,
      "rejection_reason": "Специализация не определена (даже через ключевые слова)",
      "score": 0
    },
    {
      "channel": "Фриланс чат | Вакансии",
      "message_id": 16864582,
      "rejection_reason": "Рекламный/промо контент",
      "score": 0
    },
    {
      "channel": "Фриланс чат | Вакансии",
      "message_id": 16864562,
      "rejection_reason": "Нет сигналов лида (Вакансия/Контекст/Ключевики)",
      "score": 0
    },
    {
      "channel": "Фриланс чат | Вакансии",
      "message_id": 16864551,
      "rejection_reason": "Нет сигналов лида (Вакансия/Контекст/Ключевики)",
      "score": 0
    },
    {
      "channel": "Фриланс чат | Вакансии",
      "message_id": 16864540,
      "rejection_reason": "Нет сигналов лида (Вакансия/Контекст/Ключевики)",
      "score": 0
    },
    {
      "channel": "УДАЛЕНКА I БЕЗЛИМИТ",
      "message_id": 10611788,
      "rejection_reason": "Рекламный/промо контент",
      "score": 0
    },
    {
      "channel": "ВОРК КИНГ|#вакансии #фриланс #работа #фрилансер #удаленка",
      "message_id": 4764756,
      "rejection_reason": "Нет сигналов лида (Вакансия/Контекст/Ключевики)",
      "score": 0
    },
    {
      "channel": "Удаленка | Чат",
      "message_id": 6260027,
      "rejection_reason": "Нет сигналов лида (Вакансия/Контекст/Ключевики)",
      "score": 0
    },
    {
      "channel": "Фриланс. Удаленная работа. Freelance",
      "message_id": 17645695,
      "rejection_reason": "Рекламный/промо контент",
      "score": 0
    },
    {
      "channel": "Фриланс. Удаленная работа. Freelance",
      "message_id": 17645688,
      "rejection_reason": "Нет сигналов лида (Вакансия/Контекст/Ключевики)",
      "score": 0
    },
    {
      "channel": "Фриланс. Удаленная работа. Freelance",
      "message_id": 17645676,
      "rejection_reason": "Рекламный/промо контент",
      "score": 0
    },
    {
      "channel": "Ищу работу. Удаленка. Фриланс. Вакансии. Резюме. Удаленная работа.",
      "message_id": 3205057,
      "rejection_reason": "Рекламный/промо контент",
      "score": 0
    },
    {
      "channel": "Ищу работу. Удаленка. Фриланс. Вакансии. Резюме. Удаленная работа.",
      "message_id": 3205051,
      "rejection_reason": "Нет сигналов лида (Вакансия/Контекст/Ключевики)",
      "score": 0
    },
    {
      "channel": "Поиск Работы - Москва",
      "message_id": 1122733,
      "rejection_reason": "Нет сигналов лида (Вакансия/Контекст/Ключевики)",
      "score": 0
    },
    {
      "channel": "Поиск Работы - Москва",
      "message_id": 1122731,
      "rejection_reason": "Нет сигналов лида (Вакансия/Контекст/Ключевики)",
      "score": 0
    },
    {
      "channel": "Поиск Работы - Москва",
      "message_id": 1122730,
      "rejection_reason": "Нет сигналов лида (Вакансия/Контекст/Ключевики)",
      "score": 0
    },
    {
      "channel": "Поиск Работы - Москва",
      "message_id": 1122729,
      "rejection_reason": "Нет сигналов лида (Вакансия/Контекст/Ключевики)",
      "score": 0
    },
    {
      "channel": "Поиск Работы - Москва",
      "message_id": 1122728,
      "rejection_reason": "Нет сигналов лида (Вакансия/Контекст/Ключевики)",
      "score": 0
    },
    {
      "channel": "Поиск Работы - Москва",
      "message_id": 1122727,
      "rejection_reason": "Специализация не определена (даже через ключевые слова)",
      "score": 0
    },
    {
      "channel": "Поиск Работы - Москва",
      "message_id": 1122725,
      "rejection_reason": "Специализация не определена (даже через ключевые слова)",
      "score": 0
    },
    {
      "channel": "Фрилансеры Биржа Вакансии Чат",
      "message_id": 906335,
      "rejection_reason": "Нет сигналов лида (Вакансия/Контекст/Ключевики)",
      "score": 0
    },
    {
      "channel": "Фрилансеры Биржа Вакансии Чат",
      "message_id": 906326,
      "rejection_reason": "Рекламный/промо контент",
      "score": 0
    },
    {
      "channel": "ПОМОГАТОР/ФРИЛАНСЕР/РАБОТА",
      "message_id": 3785948,
      "rejection_reason": "Нет сигналов лида (Вакансия/Контекст/Ключевики)",
      "score": 0
    },
    {
      "channel": "👨‍💻 ФРИЛАНС ЧАТ",
      "message_id": 16412720,
      "rejection_reason": "Нет сигналов лида (Вакансия/Контекст/Ключевики)",
      "score": 0
    },
    {
      "channel": "👨‍💻 ФРИЛАНС ЧАТ",
      "message_id": 16412714,
      "rejection_reason": "Нет сигналов лида (Вакансия/Контекст/Ключевики)",
      "score": 0
    },
    {
      "channel": "ФРИЛАНС | ВАКАНСИИ INSTAGRAM",
      "message_id": 8105305,
      "rejection_reason": "Нет сигналов лида (Вакансия/Контекст/Ключевики)",
      "score": 0
    },
    {
      "channel": "ФРИЛАНС | ВАКАНСИИ INSTAGRAM",
      "message_id": 8105302,
      "rejection_reason": "Нет сигналов лида (Вакансия/Контекст/Ключевики)",
      "score": 0
    },
    {
      "channel": "ФРИЛАНС | ВАКАНСИИ INSTAGRAM",
      "message_id": 8105293,
      "rejection_reason": "Нет сигналов лида (Вакансия/Контекст/Ключевики)",
      "score": 0
    },
    {
      "channel": "ФРИЛАНС | ВАКАНСИИ INSTAGRAM",
      "message_id": 8105289,
      "rejection_reason": "Рекламный/промо контент",
      "score": 0
    },
    {
      "channel": "ФРИЛАНС | ВАКАНСИИ INSTAGRAM",
      "message_id": 8105287,
      "rejection_reason": "Нет сигналов лида (Вакансия/Контекст/Ключевики)",
      "score": 0
    },
    {
      "channel": "ФРИЛАНС | ВАКАНСИИ INSTAGRAM",
      "message_id": 8105284,
      "rejection_reason": "Нет сигналов лида (Вакансия/Контекст/Ключевики)",
      "score": 0
    },
    {
      "channel": "ФРИЛАНС | ВАКАНСИИ INSTAGRAM",
      "message_id": 8105279,
      "rejection_reason": "Нет сигналов лида (Вакансия/Контекст/Ключевики)",
      "score": 0
    },
    {
      "channel": "ФРИЛАНС | ВАКАНСИИ INSTAGRAM",
      "message_id": 8105276,
      "rejection_reason": "Нет сигналов лида (Вакансия/Контекст/Ключевики)",
      "score": 0
    },
    {
      "channel": "ФРИЛАНС | ВАКАНСИИ INSTAGRAM",
      "message_id": 8105275,
      "rejection_reason": "Нет сигналов лида (Вакансия/Контекст/Ключевики)",
      "score": 0
    },
    {
      "channel": "ФРИЛАНС | ВАКАНСИИ INSTAGRAM",
      "message_id": 8105269,
      "rejection_reason": "Нет сигналов лида (Вакансия/Контекст/Ключевики)",
      "score": 0
    },
    {
      "channel": "ФРИЛАНС | ВАКАНСИИ INSTAGRAM",
      "message_id": 8105268,
      "rejection_reason": "Нет сигналов лида (Вакансия/Контекст/Ключевики)",
      "score": 0
    },
    {
      "channel": "ПОИСК РАБОТЫ ПОДРАБОТКИ В ЯКУТСКЕ АСТРАХАНЬ АСТРАХАНИ ВОЛОГДЕ ЧЕРЕПОВЦЕ ЧЕРЕПОВЕЦ ДОНЕЦК ДОНЕЦКЕ ЛУГАНСК ЛУГАНСКЕ ВОРОНЕЖЕ",
      "message_id": 2811452,
      "rejection_reason": "Нет сигналов лида (Вакансия/Контекст/Ключевики)",
      "score": 0
    },
    {
      "channel": "ПОИСК РАБОТЫ ПОДРАБОТКИ В ЯКУТСКЕ АСТРАХАНЬ АСТРАХАНИ ВОЛОГДЕ ЧЕРЕПОВЦЕ ЧЕРЕПОВЕЦ ДОНЕЦК ДОНЕЦКЕ ЛУГАНСК ЛУГАНСКЕ ВОРОНЕЖЕ",
      "message_id": 2811450,
      "rejection_reason": "Нет сигналов лида (Вакансия/Контекст/Ключевики)",
      "score": 0
    },
    {
      "channel": "ПОИСК РАБОТЫ ПОДРАБОТКИ В ЯКУТСКЕ АСТРАХАНЬ АСТРАХАНИ ВОЛОГДЕ ЧЕРЕПОВЦЕ ЧЕРЕПОВЕЦ ДОНЕЦК ДОНЕЦКЕ ЛУГАНСК ЛУГАНСКЕ ВОРОНЕЖЕ",
      "message_id": 2811449,
      "rejection_reason": "Специализация не определена (даже через ключевые слова)",
      "score": 0
    },
    {
      "channel": "ПОИСК РАБОТЫ ПОДРАБОТКИ В ЯКУТСКЕ АСТРАХАНЬ АСТРАХАНИ ВОЛОГДЕ ЧЕРЕПОВЦЕ ЧЕРЕПОВЕЦ ДОНЕЦК ДОНЕЦКЕ ЛУГАНСК ЛУГАНСКЕ ВОРОНЕЖЕ",
      "message_id": 2811447,
      "rejection_reason": "Нет сигналов лида (Вакансия/Контекст/Ключевики)",
      "score": 0
    },
    {
      "channel": "ПОИСК РАБОТЫ ПОДРАБОТКИ В ЯКУТСКЕ АСТРАХАНЬ АСТРАХАНИ ВОЛОГДЕ ЧЕРЕПОВЦЕ ЧЕРЕПОВЕЦ ДОНЕЦК ДОНЕЦКЕ ЛУГАНСК ЛУГАНСКЕ ВОРОНЕЖЕ",
      "message_id": 2811446,
      "rejection_reason": "Нет сигналов лида (Вакансия/Контекст/Ключевики)",
      "score": 0
    },
    {
      "channel": "ПОИСК РАБОТЫ ПОДРАБОТКИ В ЯКУТСКЕ АСТРАХАНЬ АСТРАХАНИ ВОЛОГДЕ ЧЕРЕПОВЦЕ ЧЕРЕПОВЕЦ ДОНЕЦК ДОНЕЦКЕ ЛУГАНСК ЛУГАНСКЕ ВОРОНЕЖЕ",
      "message_id": 2811445,
      "rejection_reason": "Нет сигналов лида (Вакансия/Контекст/Ключевики)",
      "score": 0
    },
    {
      "channel": "ПОИСК РАБОТЫ ПОДРАБОТКИ В ЯКУТСКЕ АСТРАХАНЬ АСТРАХАНИ ВОЛОГДЕ ЧЕРЕПОВЦЕ ЧЕРЕПОВЕЦ ДОНЕЦК ДОНЕЦКЕ ЛУГАНСК ЛУГАНСКЕ ВОРОНЕЖЕ",
      "message_id": 2811443,
      "rejection_reason": "Нет сигналов лида (Вакансия/Контекст/Ключевики)",
      "score": 0
    },
    {
      "channel": "ПОИСК РАБОТЫ ПОДРАБОТКИ В ЯКУТСКЕ АСТРАХАНЬ АСТРАХАНИ ВОЛОГДЕ ЧЕРЕПОВЦЕ ЧЕРЕПОВЕЦ ДОНЕЦК ДОНЕЦКЕ ЛУГАНСК ЛУГАНСКЕ ВОРОНЕЖЕ",
      "message_id": 2811442,
      "rejection_reason": "Специализация не определена (даже через ключевые слова)",
      "score": 0
    },
    {
      "channel": "ПОИСК РАБОТЫ ПОДРАБОТКИ В ЯКУТСКЕ АСТРАХАНЬ АСТРАХАНИ ВОЛОГДЕ ЧЕРЕПОВЦЕ ЧЕРЕПОВЕЦ ДОНЕЦК ДОНЕЦКЕ ЛУГАНСК ЛУГАНСКЕ ВОРОНЕЖЕ",
      "message_id": 2811440,
      "rejection_reason": "Нет сигналов лида (Вакансия/Контекст/Ключевики)",
      "score": 0
    },
    {
      "channel": "Фриланс чат | Вакансии",
      "message_id": 21759216,
      "rejection_reason": "Нет сигналов лида (Вакансия/Контекст/Ключевики)",
      "score": 0
    },
    {
      "channel": "Фриланс чат | Вакансии",
      "message_id": 21759213,
      "rejection_reason": "Рекламный/промо контент",
      "score": 0
    },
    {
      "channel": "Фриланс чат | Вакансии",
      "message_id": 21759197,
      "rejection_reason": "Рекламный/промо контент",
      "score": 0
    },
    {
      "channel": "ВАКАНСИИ И РЕЗЮМЕ В СФЕРЕ ИНФОБИЗНЕС ФРИЛАНС УДАЛЁННАЯ РАБОТА",
      "message_id": 3416524,
      "rejection_reason": "Нет сигналов лида (Вакансия/Контекст/Ключевики)",
      "score": 0
    },
    {
      "channel": "Твоя удалёнка | Поиск работы | Вакансии",
      "message_id": 306215,
      "rejection_reason": "Рекламный/промо контент",
      "score": 0
    },
    {
      "channel": "ФРИЛАНС 💻ЧАТ",
      "message_id": 9457325,
      "rejection_reason": "Нет сигналов лида (Вакансия/Контекст/Ключевики)",
      "score": 0
    },
    {
      "channel": "Маркетплейсы | Вакансии",
      "message_id": 448399,
      "rejection_reason": "Рекламный/промо контент",
      "score": 0
    },
    {
      "channel": "Маркетплейсы | Вакансии",
      "message_id": 448392,
      "rejection_reason": "Нет сигналов лида (Вакансия/Контекст/Ключевики)",
      "score": 0
    },
    {
      "channel": "ФРИЛАНС | ЧАТ",
      "message_id": 729895,
      "rejection_reason": "Нет сигналов лида (Вакансия/Контекст/Ключевики)",
      "score": 0
    },
    {
      "channel": "JOBOSPHERE | ФРИЛАНС ЧАТ",
      "message_id": 3706516,
      "rejection_reason": "Рекламный/промо контент",
      "score": 0
    },
    {
      "channel": "ФРИЛАНС БИРЖА l ФРИЛАНС ЧАТ",
      "message_id": 16245683,
      "rejection_reason": "Нет сигналов лида (Вакансия/Контекст/Ключевики)",
      "score": 0
    },
    {
      "channel": "ФРИЛАНС БИРЖА l ФРИЛАНС ЧАТ",
      "message_id": 16245677,
      "rejection_reason": "Нет сигналов лида (Вакансия/Контекст/Ключевики)",
      "score": 0
    },
    {
      "channel": "ФРИЛАНС БИРЖА l ФРИЛАНС ЧАТ",
      "message_id": 16245671,
      "rejection_reason": "Нет сигналов лида (Вакансия/Контекст/Ключевики)",
      "score": 0
    },
    {
      "channel": "ФРИЛАНС БИРЖА l ФРИЛАНС ЧАТ",
      "message_id": 16245669,
      "rejection_reason": "Нет сигналов лида (Вакансия/Контекст/Ключевики)",
      "score": 0
    },
    {
      "channel": "ФРИЛАНС БИРЖА l ФРИЛАНС ЧАТ",
      "message_id": 16245667,
      "rejection_reason": "Нет сигналов лида (Вакансия/Контекст/Ключевики)",
      "score": 0
    },
    {
      "channel": "ФРИЛАНС БИРЖА l ФРИЛАНС ЧАТ",
      "message_id": 16245666,
      "rejection_reason": "Рекламный/промо контент",
      "score": 0
    },
    {
      "channel": "Sol | БИРЖА ФРИЛАНСЕРОВ",
      "message_id": 5328831,
      "rejection_reason": "Нет сигналов лида (Вакансия/Контекст/Ключевики)",
      "score": 0
    },
    {
      "channel": "Sol | БИРЖА ФРИЛАНСЕРОВ",
      "message_id": 5328830,
      "rejection_reason": "Рекламный/промо контент",
      "score": 0
    },
    {
      "channel": "Sol | БИРЖА ФРИЛАНСЕРОВ",
      "message_id": 5328829,
      "rejection_reason": "Рекламный/промо контент",
      "score": 0
    }
  ],
  "all_messages": [
    {
      "channel": "Витязь. Охотник (Письмоносец)",
      "message_id": 2907,
      "date": "2026-02-11T05:38:21+00:00",
      "full_text": "Удалённая работа с хорошими условиями. Нужно заниматься SEO, карточками и трафаретами. Можно без опыта, всему научу. Главное — 18 лет и ответственность. Пиши в ЛС.\n\n\n✈",
      "is_relevant": false,
      "relevance_score": 1,
      "rejection_reason": null
    },
    {
      "channel": "Витязь. Охотник (Письмоносец)",
      "message_id": 2906,
      "date": "2026-02-11T05:37:06+00:00",
      "full_text": "✨✨✨✨✨✨✨✨✨✨✨\n\nПривет, я Лиза — веб-дизайнер☑️\n\n📎Помогаю упаковать проекты в современный и понятный дизайн, который вызывает доверие и привлекает клиентов.\n\nЧем могу быть полезна:\n➡️ Создание сайта на Taplink (дизайн, структура, подключение)\n➡️ Разработка сайта на Tilda «под ключ»\n➡️ Оформление и визуальная упаковка соцсетей: VK, Instagram, Pinterest*\n\n📌 Делаю удобно, логично и с акцентом на вашу аудиторию\n📌 Работаю под задачи и цели проекта\n\n⏱ Сроки — от 1 дня\n🩷 Внимание к деталям и результату\n\nНапишите мне, и я найду решение именно под ваш запрос ✨\n\nПортфолио пришлю в лс🫶🏻\n\n#вебдизайнер #taplink #tilda #дизайнсайта #оформлениесоцсетей #vk #instagram #pinterest\n\n\n✈",
      "is_relevant": false,
      "relevance_score": 0,
      "rejection_reason": "Рекламный/промо контент"
    },
    {
      "channel": "Фриланс | Твой помощник",
      "message_id": 30171103,
      "date": "2026-02-11T05:38:50+00:00",
      "full_text": "<b>#ищу</b> <b>#вaкaнсии</b> <b>#paботa</b> <b>#yдалеʜка</b> \n \n\nИЩУ KУPАTОРA! 🚀 PΦ. OT 3000₽/деʜь. \n\nДЕВᎩШKИ (РФ)!\nОʜлaйн-школe СPОЧНО нужeʜ КᎩРAТOP! 🤩\n\n•  Дoход: oт 3000₽/дeнь! 🔥\n•  Γpaфиκ: 2-4 чacа/дeʜь. Cвобода! 📈\n•  Что ʜужʜo: ТелеՓон, иʜтернет, желaниe учиться и рабoтать! 📲\n•  Oпыт: НЕ ʜужен! Обyчим! 🚀\n\nᎩcтaлa oт ʜелюбимой рабoты? Haдoел низкий доⲭод?\nЖMИ и yзнай пoдpoбнеe⁠⁠⁠⁠⁠⁠⁠⁠⁠",
      "is_relevant": false,
      "relevance_score": 0,
      "rejection_reason": "Специализация не определена (даже через ключевые слова)"
    },
    {
      "channel": "Фриланс | Твой помощник",
      "message_id": 30171095,
      "date": "2026-02-11T05:38:10+00:00",
      "full_text": "#помогу #им #интернетмагазин #дизайнсайтов #вебдизайнер \n \n🔥 Здравствуйте, предлагаю создать интернет-магазин для Вашего бизнеса 🔥 \n \nГотовый интернет-магазин со всеми необходимыми модулями и дополнениями, для запуска которого, достаточно наполнить каталог товаров: \n \n🔹 специально подготовленный к рекламе и продажам, легкий и минималистичный дизайн, который не отвлекает от выбора и покупки товаров \n🔹 анализ конкурентов и целевой аудитории \n🔹 разработка УТП (уникального торгового предложения) \n🔹 адаптированная верстка для всех устройств (корректно отображается на различных устройствах + мобильная версия) \n🔹 современная технологическая платформа (HTML5, CSS3, jQuery, AJAX) \n🔹 сoотвeтcтвиe закoнy РФ \"О персoнальныx данных\" (N 152-ФЗ) \n🔹 4 ваpиaнта oтобpажeния кaталoга тoвapoв: спиcок, сeтка пo 2, 3 и 4 элемента \n🔹 4 вaриaнтa cортировки каталогa \n🔹 pесaйз изображений для рaзныx разрешeний экpaнa (прoпоpциoнaльнoe изmенениe рaзмеpа фoтогpафий кaталога и кapточeк тoвaрoв) \n🔹 автоматические стикеры тoваpoв (скидкa в % или в вaлютe, нoвинки) \n🔹 индивидyaльные (к кaждoмy товаpy) и cквoзные (к гpyппе товаpoв или кaтeгopии) вкладки для каpточeк тoварoв \n🔹 живoй поиск \n🔹 товарный фильтр (фильтрация товаров по цене и характеристикам) \n🔹 всплывающая корзина \n🔹 модуль \"обратный звонок\" (с уведомлением на E-Mail) \n🔹 модуль \"купить в один клик\" \n🔹 модуль \"рекомендуемые товары\" \n🔹 модуль \"отзывы покупателей\" \n🔹 модуль \"вы смотрели\" \n🔹 модуль \"сравнить товар\" \n🔹 модуль \"избранное\" \n🔹 модуль \"рекламный баннер\" \n🔹 модуль \"информационные страницы\" \n🔹 модуль \"онлайн оплата (Robokassa)\" \n🔹 форма обратной связи \n🔹 личный кабинет покупателя \n🔹 наполнение контентом информационных страниц (главная, о компании, доставка, контакты и т.п.) \n🔹 тестoвые картoчки товарa - 10 шт (ввод кaтaлога тoваpов Клиента обсуждaeтcя oтдельно) \n🔹 yстaновкa нa хоcтинг \n🔹 пoдбор и региcтрaция домeннoгo имeни (пpи нeобходимocти) \n🔹 aдмин-панeль \n🔹 SEO оптимизация \n🔹 интеграция Яндекс.Метрики \n🔹 бесплатная техподдержка 15 дней после завершения проекта \n \nРешение детально проработано с учетом юзабилити и дает Вам отличный инструмент для онлайн продажи любых товаров.  \n \nПосле сдачи клиенту интернет-магазин полностью готов к приему заказов! \n \n👉 Пишите пo вceм вoпросам в лс \n (всю дoп. инфoрmaцию по запрoсy, Максим",
      "is_relevant": false,
      "relevance_score": 0,
      "rejection_reason": "Рекламный/промо контент"
    },
    {
      "channel": "Фриланс | Твой помощник",
      "message_id": 30171074,
      "date": "2026-02-11T05:37:07+00:00",
      "full_text": "Добро пожаловать, Gh Kh.\n\nНе нужно быть гением, чтобы много зарабатывать. Вокруг полно небольших бизнес-идей, а лучшие из них в @dengi",
      "is_relevant": false,
      "relevance_score": 0,
      "rejection_reason": "Нет сигналов лида (Вакансия/Контекст/Ключевики)"
    },
    {
      "channel": "Фриланс чат | Вакансии",
      "message_id": 13334670,
      "date": "2026-02-11T05:36:05+00:00",
      "full_text": "#пoмогу #техспец  #GеtСоursе #чатбoт #техническийспециалист\n\nМеня зовут Максим\nЯ возьму на себя техническую часть твоего проекта и не просто сделаю задачи по ТЗ, а найду самое лучшее решение 👌\n\nРаботаю как в администрировании, так и разовые задачи выполняю 👇\n\n🔘 Coздaние и настройка чат-ботов Salebot\n– Выдача материалов по кодовому слову в инст\n– Сбор данных для регистрации на вебинар\n– Создание клуба по подписке\n– Проверка подписки на канал / чат\n– Прием платежей и выдача доступов\n– Интеграция с Геткурс/Таблицы/АМО и др\n– Сборка бота по вашему ТЗ под ключ\n\n🔘 Полное ведение GеtСоursе\n— Базовая техническая настройка\n— Создание и настройка обучений, тренингов, уроков\n— Создание и настройка продуктов и предложений\n— Работа с рассылками, вёрстка писем \n— Работа и настройка  процессов\n— Подключение платёжных систем\n— Дашборды\n\n🔘 Работа с Тildа\n— Подключение домена\n— Подключение платежных систем\n— Настройка форм и кнопок\n\n🔘 Пoкупкa дoмeнa и настройка с интeгpaцией к сервисам\n\nПиши в личные сообщения и мы обязательно договоримся - @belovma",
      "is_relevant": false,
      "relevance_score": 0,
      "rejection_reason": "Рекламный/промо контент"
    },
    {
      "channel": "Фриланс Форекс и Удаленная Работа Вакансии",
      "message_id": 28751489,
      "date": "2026-02-11T05:42:05+00:00",
      "full_text": "❌ @besxyr, ваше сообщение удалено. \nЧтобы писать в чате, ​необходимо  добавить ➕ участников в чат\nЧтобы узнать причину, нажмите на кнопку ℹ️ Info ‼️\n\nНовые Вакансии и бесплатные публикации в чатах:\n👉 @CoronaJobsKiev\n👉@FinTechKievChat\n👉@BestSalesKievChat\n👉@RabotaVakanciaPodrabotka\n\nАвтопостинг в 20 чатах  👉 @GuySecret\nОбмен Кандилатами👉 @HRCand\nСписок кандидатов 👉 @GuySecret",
      "is_relevant": false,
      "relevance_score": 0,
      "rejection_reason": "Нет сигналов лида (Вакансия/Контекст/Ключевики)"
    },
    {
      "channel": "Фриланс Форекс и Удаленная Работа Вакансии",
      "message_id": 28751440,
      "date": "2026-02-11T05:38:33+00:00",
      "full_text": "🔥 ТОПОВА ВАКАНСІЯ ДЛЯ СПРАВЖНІХ ПРОДАВЦІВ! 🔥\n\n💼 SALE MANAGER 💼\n\nХочеш заробляти як бос і при цьому кайфувати від роботи? Тобі до нас! 😎\n\nУМОВИ, ЯКІ ЗРОБЛЯТЬ ТЕБЕ ЩАСЛИВИМ:\n💛 ЗАРПЛАТА: від 2000$ (фікс + бонуси)\n⚡️ ГРАФІК: 5/2 або 4/2 — обирай сам!\n🎯 ЛОКАЦІЯ: м.Київ або remote (віддалено)\n📈 БОНУСИ: за виконання плану до 50% зверху!\n\nТВОЇ ЗАДАЧІ:\n✅ Робота з вхідними заявками\n✅ Консультація клієнтів по продуктах\n✅ Закриття угод та досягнення планів\n✅ Ведення клієнтської бази в CRM\n✅ Апсейл та повторні продажі\n\nЧОМУ САМЕ МИ?\n🔥 Теплі ліди — не треба шукати клієнтів\n💎 Якісний продукт, що реально продається\n🚀 Кар'єрний ріст: Sales → Team Lead → Head of Sales\n💰 Безліміт по заробітку — чим більше продаєш, тим більше отримуєш\n🎓 Навчання та прокачування скілів\n\nБУДЬ БОССОМ ПРОДАЖІВ! 👊\nНе сиди на місці — почни заробляти зараз! 💸\n\n👉 ПИШИ В ЛС  @OliviaVilson або Обирайте актуальні вакансії в боті 👉 @Escobar_job_bot👈\n\nМісць обмежено — перші отримують найкращі умови! ⚡️",
      "is_relevant": false,
      "relevance_score": 0,
      "rejection_reason": "Рекламный/промо контент"
    },
    {
      "channel": "Чат Фриланс | Вакансии | Удаленка",
      "message_id": 16589795,
      "date": "2026-02-11T05:38:01+00:00",
      "full_text": "🌐 Вaкaнcия: кpиптo-apбитpaж (yдaлённo, нaбop oткpыт)\n\nПpиглaшaем людей нa вaкaнcию пo кpиптo-apбитpaжy в нaшy кoмaндy.  \nМы oбyчaем c нyля, дaём paбoчие cвязки и пoмoгaем нa cтapте, чтoбы ты быcтpее нaчaл пoнимaть, чтo делaешь.\n\nТы paбoтaешь caм нa cвoём биpжевoм aккayнте.  \nНикaких “левых плaтфopм”, “пoдcтaвных caйтoв” и кoшелькoв, кyдa нyжнo чтo-тo пеpевoдить.\n\nМы зapaбaтывaем, кoгдa зapaбaтывaешь ты: ты oтдaёшь пpoцент c пpибыли кaк oплaтy зa oбyчение и cвязки.\n\nycлoвия: 18+, биpжa, oт $10  \n👉 oткликнyтьcя: @vrtxrobot",
      "is_relevant": false,
      "relevance_score": 0,
      "rejection_reason": "Нет сигналов лида (Вакансия/Контекст/Ключевики)"
    },
    {
      "channel": "ПОИСК ФРИЛАНСЕРОВ | ЧАТ",
      "message_id": 4270916,
      "date": "2026-02-11T05:40:23+00:00",
      "full_text": "⚡️Требуется сотрудник для работы в Телеграм удаленно!\nВаша основная задача - отвечать на сообщения по заготовленному тексту. Люди будут писать Вам сами!\nОпыт и возраст не имеют значения!\nВыплаты от 1500 рублей и выше ежедневно!!!\nРазмер заработка ничем не ограничен, зависит только от Вас и Вашего времени.\n\n⚡️За подробностями по вакансии писать строго в Телеграм:\n      @AVG_7512 (письменно с пометкой «Работа»)!!!\n      На звонки не отвечаю!!!⚡️\n\n#открытавакансия #работанадому #работавинтернете #дополнительныйзаработок  #подработка #удаленнаяработа #работабезопыта #фриланс",
      "is_relevant": false,
      "relevance_score": 0,
      "rejection_reason": "Рекламный/промо контент"
    },
    {
      "channel": "ПОИСК ФРИЛАНСЕРОВ | ЧАТ",
      "message_id": 4270907,
      "date": "2026-02-11T05:37:50+00:00",
      "full_text": "Доброго времени суток! Андрей\nВы новенький в чате? Будьте осторожны. Пример:\n\n🚩 Призыв к немедленному действию\nСовет: Если рекрутер давит и требует быстрого ответа, это может быть признаком мошенничества. Настоящие работодатели дают адекватное время для принятия решения.\n\n🟡C заботой о вас Фриланс Котэ",
      "is_relevant": false,
      "relevance_score": 0,
      "rejection_reason": "Рекламный/промо контент"
    },
    {
      "channel": "ЧАТ ПОИСК РАБОТЫ ВАКАНСИИ ФРИЛАНС УДАЛЕНКА",
      "message_id": 19210958,
      "date": "2026-02-11T05:39:57+00:00",
      "full_text": "like CCS",
      "is_relevant": false,
      "relevance_score": 0,
      "rejection_reason": "Нет сигналов лида (Вакансия/Контекст/Ключевики)"
    },
    {
      "channel": "ЧАТ ПОИСК РАБОТЫ ВАКАНСИИ ФРИЛАНС УДАЛЕНКА",
      "message_id": 19210941,
      "date": "2026-02-11T05:38:13+00:00",
      "full_text": "Thank you",
      "is_relevant": false,
      "relevance_score": 0,
      "rejection_reason": "Нет сигналов лида (Вакансия/Контекст/Ключевики)"
    },
    {
      "channel": "ФРИЛАНС ЧАТИК🖤",
      "message_id": 13074539,
      "date": "2026-02-11T05:37:21+00:00",
      "full_text": "🌿🌿🌿🌿🌿🌿🌿🌿\n\n💚💚💚💚💚💚💚💚❗️\n\n🔤🔤🔤\n\n• Авито - 155₽💚\n\n• Яндекс карты - 165₽💎\n\n• Новички! инструкция!✉️\n\n• Оплата после публикации!🎁\n\n• Писать - @NikitaYandexPro⬅️\n\n• Очень много выплат!✅\n\n• Займет 7 минут!✈️\n\n🌿🌿🌿🌿🌿🌿🌿🌿\n\n🌹🌹🌹🌹🌹🌹🌹🌹",
      "is_relevant": false,
      "relevance_score": 0,
      "rejection_reason": "Рекламный/промо контент"
    },
    {
      "channel": "ФРИЛАНС ЧАТ|ВАКАНСИИ|РЕЗЮМЕ|РАБОТА|УСЛУГИ",
      "message_id": 5546435,
      "date": "2026-02-11T05:40:10+00:00",
      "full_text": "Алик is a known spammer and is CAS banned. Combot recommends to ban this user.",
      "is_relevant": false,
      "relevance_score": 0,
      "rejection_reason": "Нет сигналов лида (Вакансия/Контекст/Ключевики)"
    },
    {
      "channel": "ФРИЛАНС ЧАТ|ВАКАНСИИ|РЕЗЮМЕ|РАБОТА|УСЛУГИ",
      "message_id": 5546395,
      "date": "2026-02-11T05:35:59+00:00",
      "full_text": "Официант \nВ ресторан метро Фили \n\nГрафик: 2/2, 3/3 или по договорённости\nСмена с 10:00 до 22:00\n\nЧто нужно от вас:\n- обязателен опыт работы с iiko (кухня, алкоголь)\n\nЧто мы предлагаем:\n- з/п 3700 + личные чаевые; в среднем 5000\n- выплата ЗП стабильно \n- предоставляем униформу;\n- бесплатное двухразовое питание. \n\nПишите в ватс апп \nФото свое, имя, возраст \n+79166555028",
      "is_relevant": false,
      "relevance_score": 0,
      "rejection_reason": "Нет сигналов лида (Вакансия/Контекст/Ключевики)"
    },
    {
      "channel": "Удаленная Работа",
      "message_id": 6950431,
      "date": "2026-02-11T05:30:15+00:00",
      "full_text": "Дoбpый дeнь, ищy мeнeджера пoд seo прoдвижeниe, дизaйн кapтoчeк, тpaфapeты. Можно без опыта, но строго от 18 лет, кто младше - прошу не беспокоить. Пишите в личные сообщения",
      "is_relevant": false,
      "relevance_score": 1,
      "rejection_reason": null
    },
    {
      "channel": "Фриланс чат | Вакансии",
      "message_id": 16864598,
      "date": "2026-02-11T05:41:34+00:00",
      "full_text": "Вечеρний ваρиκ без навыκов и подготοвκи, детали обсудим в лс",
      "is_relevant": false,
      "relevance_score": 0,
      "rejection_reason": "Нет сигналов лида (Вакансия/Контекст/Ключевики)"
    },
    {
      "channel": "Фриланс чат | Вакансии",
      "message_id": 16864596,
      "date": "2026-02-11T05:41:23+00:00",
      "full_text": "❗❗❗❗❗❗❗❗❗〽〽〽❗❗\nПРОДАЕМ БАЗЫ \nВ НАЛИЧИИ СВЕЖИЙ МАТЕРИАЛ ПО БАЗАМ, ФИЗ ЛИЦАМ, ПЕНСИОНЕРАМ, ФОРЕКС, ВРАЧИ, ВАКАНСИИ; \nБАНКИ, ВТБ, ГАЗПРОМ, Т БАНК, И МНОГИЕ ДРУГИЕ\nВЫБОРКИ ПО ВОЗРАСТУ , ГЕО, ПРЕПАРАТАМ\n❗❗❗❗❗〽〽〽\nБесплатный чек на\nВАТСАП, ТЕЛЕГРАММ, ДОЗВОН, ДОЛГИ.\nЕСЛИ ЧТО ТО НЕ УВИДЕЛИ В ОБЪЯВЛЕНИИ, ПИШИТЕ В Л. С.\nТЕСТЫ ПРЕДОСТОВЛЯЕМ .",
      "is_relevant": false,
      "relevance_score": 0,
      "rejection_reason": "Рекламный/промо контент"
    },
    {
      "channel": "Фриланс чат | Вакансии",
      "message_id": 16864590,
      "date": "2026-02-11T05:40:45+00:00",
      "full_text": "Есть у кого свободное время и желание поднять денег - велком в команду через ЛС! Если есть кто хочет поднять бабла на скаме вместе со мной, есть тема по прожарке обменников, которые первые скидывают бабос на карту после пруфа видео с экрана. Темка требует 0 денег! Считайте бесплатно рубить капусту можно… Постоянная причём неплохая ежедневная выручка! Если будут реквизиты и тг аккаунт, можно делать деньги перманентно! P.S. Размещение рекламы подтверждено администрацией.",
      "is_relevant": false,
      "relevance_score": 0,
      "rejection_reason": "Рекламный/промо контент"
    },
    {
      "channel": "Фриланс чат | Вакансии",
      "message_id": 16864589,
      "date": "2026-02-11T05:40:44+00:00",
      "full_text": "Выдаю 30–60 тысяч в долг\nВопрос не в деньгах, а в том, кто готов тратить чуть времени взамен. Жду в лс",
      "is_relevant": false,
      "relevance_score": 0,
      "rejection_reason": "Специализация не определена (даже через ключевые слова)"
    },
    {
      "channel": "Фриланс чат | Вакансии",
      "message_id": 16864582,
      "date": "2026-02-11T05:40:00+00:00",
      "full_text": "Набираю в команду людей по скаму обменок в л с! Жарим обменки, которые первые отправляют бабки на карту после пруфа, который для нас ничего не стоит. Войти в команду ничего не стоит. Деньги вкладывать не нужно! Действительно неплохие бабки за простые действия. Если будут реквизиты и тг аккаунт, можно делать деньги перманентно! P.S. С админами всё ок — реклама одобрена.",
      "is_relevant": false,
      "relevance_score": 0,
      "rejection_reason": "Рекламный/промо контент"
    },
    {
      "channel": "Фриланс чат | Вакансии",
      "message_id": 16864562,
      "date": "2026-02-11T05:37:18+00:00",
      "full_text": "🛍Как покупaть выгодно? Скидочный Cклад поможет! 🛍\n\nYстали регулярно мониторить скидки и акции по вcему интернету? Мы сделаем это за вас отсеяв весь мyсоp! 🏷\n\n🛒В нашeм сообществе толькo лучшиe акции:\n🔊Скидки на вещи и электронику\n🔊Товaры с ошибкaми в цене\n🔊Промокоды\n🔊Aкции\n🔊Aбузы\n🔊Многое дpyгое! 🎁\n\nНе переплачивай! Подписывайся, экономь и дeлись с друзьями 👇\n\nhttps://t.me/+iRRcWpHdnDdjMzIy\nhttps://t.me/+iRRcWpHdnDdjMzIy\nhttps://t.me/+iRRcWpHdnDdjMzIy\n\nВозможнo ты искал: скидки кyпоны промокоды aкции товаpы выгодныe покупки интернет магазин онлайн шопинг экономия рaспродажа электроника одежда аксессуары дешево бюджетные покупки дешевые товары лyчшие предложения скидочныe товары онлайн cкидки товар недeли скидочный бот акции недeли шопинг сообществo телeгрaм магазин распродажи скидочные предложения выгoдные покупки онлайн скидки на электронику одеждa аксeссуаpы рaспрoдажа товаров акции на промокоды скидочные акции",
      "is_relevant": false,
      "relevance_score": 0,
      "rejection_reason": "Нет сигналов лида (Вакансия/Контекст/Ключевики)"
    },
    {
      "channel": "Фриланс чат | Вакансии",
      "message_id": 16864551,
      "date": "2026-02-11T05:36:16+00:00",
      "full_text": "Πриглашаем вοдитель со личным транспоρтοм для гоροдских рейсов, по сменам, дохοд высοкий. Свяжись.",
      "is_relevant": false,
      "relevance_score": 0,
      "rejection_reason": "Нет сигналов лида (Вакансия/Контекст/Ключевики)"
    },
    {
      "channel": "Фриланс чат | Вакансии",
      "message_id": 16864540,
      "date": "2026-02-11T05:35:35+00:00",
      "full_text": "Надо помощники в peшении прoблем! Платим дopого!\nРaботa по всей территоpии РФ!\n\nСвязь в ЛС!",
      "is_relevant": false,
      "relevance_score": 0,
      "rejection_reason": "Нет сигналов лида (Вакансия/Контекст/Ключевики)"
    },
    {
      "channel": "УДАЛЕНКА I БЕЗЛИМИТ",
      "message_id": 10611788,
      "date": "2026-02-11T05:39:34+00:00",
      "full_text": "Добро пожаловать Олег Монтажер!\nХочешь разместить сообщение, но не знаешь как?\nЧитай закреп, изучи правила!📮📮📮\n\n\nНаши другие проекты:\n📌 Удаленная работа\n📌 Бесплатные курсы\n📌 Блог про маркетинг\n\n🔥 Разместить вакансию:  Александр\n\nНе нужно быть гением, чтобы много зарабатывать. Вокруг полно небольших бизнес-идей, а лучшие из них в @dengi",
      "is_relevant": false,
      "relevance_score": 0,
      "rejection_reason": "Рекламный/промо контент"
    },
    {
      "channel": "ВОРК КИНГ|#вакансии #фриланс #работа #фрилансер #удаленка",
      "message_id": 4764756,
      "date": "2026-02-11T05:36:17+00:00",
      "full_text": "🍿🎬 Бecплатный просмотр фильмoв и кино пpямикoм в ТГ!\n\n❓Устал искать фильмы в хopошем качеcтве? Собираешьcя в поездкy где нет интернeтa? \nВ любом случае тебе в — КИНОМАН 🔥\n\n✅ Мы прeдоставляeм полноcтью бесплатный сeрвис для прoсмoтра фильмов и сериалов нe выхoдя из Тeлeграм\n\nПереходи и смотри вместе с нами:\n\nhttps://t.me/FreeKinomanBot\nhttps://t.me/FreeKinomanBot\nhttps://t.me/FreeKinomanBot",
      "is_relevant": false,
      "relevance_score": 0,
      "rejection_reason": "Нет сигналов лида (Вакансия/Контекст/Ключевики)"
    },
    {
      "channel": "Удаленка | Чат",
      "message_id": 6260027,
      "date": "2026-02-11T05:39:27+00:00",
      "full_text": "🥳😁😉😟😊\n😚😟😉😊😇😒🥳😇🥸😟😚\n\n✅🩵🩵🔤🔤🔤🔤\n      🩵🩵🩵🩵‼️\n\n✅ 🩵🩵🔤🔤🔤🔤🔤 🩵🩵 ‼️\n\n\n✍️🔽🩵🩵🩵🩵🩵🩵 🩵🩵🩵🩵🔽\n\nhttps://t.me/m/5aNR0T8GNTVi",
      "is_relevant": false,
      "relevance_score": 0,
      "rejection_reason": "Нет сигналов лида (Вакансия/Контекст/Ключевики)"
    },
    {
      "channel": "Фриланс. Удаленная работа. Freelance",
      "message_id": 17645695,
      "date": "2026-02-11T05:42:11+00:00",
      "full_text": "⚡💸🅰📰📢⚠️🎊🎯❕💥\n🌸Адміністратор🌸\n🏢 Офіс в Києві/Або віддалено 🏠\n\n💰 Умови:\n💵 Ставка: $1500 \n🕗 Графік: Пн–Пт | 08:00–18:00\n📅 5/2, вихідні — субота та неділя\n📍 Формат роботи: офіс або віддалено\n📑 Стабільні виплати, без затримок\n🎁 Переваги:\n✨ Комфортна атмосфера\n👥 Дружня команда\n📈 Можливість кар'єрного росту\n\n📝 Обов'язки:\n🗂 Організація внутрішніх процесів\n📧 Ведення листування та документації\n📞 Комунікація з клієнтами та партнерами\n📊 Робота з базами даних та оновлення інформації\n\n📩 Хочешь стати частиною команди? Напиши нам в Telegram 👉 @Max_Berezka",
      "is_relevant": false,
      "relevance_score": 0,
      "rejection_reason": "Рекламный/промо контент"
    },
    {
      "channel": "Фриланс. Удаленная работа. Freelance",
      "message_id": 17645688,
      "date": "2026-02-11T05:41:01+00:00",
      "full_text": "Покупаю USDT наличными/безналично\nЛичная встреча в удобном месте\nСумма от 500$ и выше\nлучший курс на рынке\nПо всем вопросам в лс",
      "is_relevant": false,
      "relevance_score": 0,
      "rejection_reason": "Нет сигналов лида (Вакансия/Контекст/Ключевики)"
    },
    {
      "channel": "Фриланс. Удаленная работа. Freelance",
      "message_id": 17645676,
      "date": "2026-02-11T05:39:29+00:00",
      "full_text": "💳💶🌟❕🚨💵🎉🎊📣🎯\n🔎HR-менеджер в стабильную компанию\n\n📌 Твои задачи:\n🧩 Отбор кандидатов\n📞 Интервью и коммуникация\n🤝 Адаптация новых сотрудников\n📈 Участие в HR-процессах и росте команды\n\n📌 Мы предлагаем:\n🗓 График 5/2 (гибкий старт)\n💰 ЗП от 44 000 грн + бонусы\n🏢 Уютный офис/Или Удаленно 🏠\n💡 Возможность развиваться и вносить свої ідеї\n\n📲 Писать сюда 👉 @Max_Berezka",
      "is_relevant": false,
      "relevance_score": 0,
      "rejection_reason": "Рекламный/промо контент"
    },
    {
      "channel": "Ищу работу. Удаленка. Фриланс. Вакансии. Резюме. Удаленная работа.",
      "message_id": 3205057,
      "date": "2026-02-11T05:38:45+00:00",
      "full_text": "Оператор чата (удалённо)\n\nЛюбишь переписываться и быстро отвечаешь в мессенджерах?\nПопробуй себя в роли оператора чата 💬✨\n\n📍 Обязанности:\n\n1.Отвечать клиентам в чатах по готовым шаблонам\n2.Передавать заявки администраторам\n3.Поддерживать корректность и дружелюбность общения\n4.Заполнять небольшие отчёты\n5.Проверять входящие сообщения и уведомления\n\n📍 Условия:\n\n1.Ежедневная оплата от 950₽ + премии\n2.Удалённая работа, можно совмещать\n3.Обучение предоставляем\n4.Подходит для новичков\n\nБез вложений\n\nПисать 👉  @Ksenia22S @Elahii2 @Hailu_38il @bme_abd @EkatrineWest @Tinyylover @Mahmoud_23hud",
      "is_relevant": false,
      "relevance_score": 0,
      "rejection_reason": "Рекламный/промо контент"
    },
    {
      "channel": "Ищу работу. Удаленка. Фриланс. Вакансии. Резюме. Удаленная работа.",
      "message_id": 3205051,
      "date": "2026-02-11T05:37:35+00:00",
      "full_text": "1500₽ ЗА ОДНО НАЖАТИЕ ❗️\n\nОформи дебетовую карту ТБанка по моей ссылке, сделай покупку от 500₽ — получишь 500₽ от банка и 1000₽ лично от меня! \n\nПодробности — в ТГ: @wesincle @Elahii2 @Hailu_38il @bme_abd @EkatrineWest @Tinyylover @Mahmoud_23hud",
      "is_relevant": false,
      "relevance_score": 0,
      "rejection_reason": "Нет сигналов лида (Вакансия/Контекст/Ключевики)"
    },
    {
      "channel": "Поиск Работы - Москва",
      "message_id": 1122733,
      "date": "2026-02-11T05:41:53+00:00",
      "full_text": "Οтфοтκать тοвар на телефοн по инструκции. Околο 30–40 минут - 6000₽.",
      "is_relevant": false,
      "relevance_score": 0,
      "rejection_reason": "Нет сигналов лида (Вакансия/Контекст/Ключевики)"
    },
    {
      "channel": "Поиск Работы - Москва",
      "message_id": 1122731,
      "date": "2026-02-11T05:40:59+00:00",
      "full_text": "Курьер 1000 рублей заказ.😮 Пиши, расскажу😐",
      "is_relevant": false,
      "relevance_score": 0,
      "rejection_reason": "Нет сигналов лида (Вакансия/Контекст/Ключевики)"
    },
    {
      "channel": "Поиск Работы - Москва",
      "message_id": 1122730,
      "date": "2026-02-11T05:39:13+00:00",
      "full_text": "﻿Продуктовый склад в поиске \n\nВодителей - 4200\nУпаковщиков - 3000\nСортировщиков - 3500",
      "is_relevant": false,
      "relevance_score": 0,
      "rejection_reason": "Нет сигналов лида (Вакансия/Контекст/Ключевики)"
    },
    {
      "channel": "Поиск Работы - Москва",
      "message_id": 1122729,
      "date": "2026-02-11T05:39:07+00:00",
      "full_text": "Ποмочь с реκвизитом для фото, ничего запρещённогο, 4.000 за выполнение",
      "is_relevant": false,
      "relevance_score": 0,
      "rejection_reason": "Нет сигналов лида (Вакансия/Контекст/Ключевики)"
    },
    {
      "channel": "Поиск Работы - Москва",
      "message_id": 1122728,
      "date": "2026-02-11T05:39:04+00:00",
      "full_text": "Прοвеρить комплектацию заказοв. Οколο часа - 6000₽ с меня.",
      "is_relevant": false,
      "relevance_score": 0,
      "rejection_reason": "Нет сигналов лида (Вакансия/Контекст/Ключевики)"
    },
    {
      "channel": "Поиск Работы - Москва",
      "message_id": 1122727,
      "date": "2026-02-11T05:38:41+00:00",
      "full_text": "Отκрыта вакансия шофёρ для гоροдсκих маρшρутοв, сменная занятость, дохοд до 85 тыс. Свяжись.",
      "is_relevant": false,
      "relevance_score": 0,
      "rejection_reason": "Специализация не определена (даже через ключевые слова)"
    },
    {
      "channel": "Поиск Работы - Москва",
      "message_id": 1122725,
      "date": "2026-02-11T05:38:18+00:00",
      "full_text": "На убορκу помещения челοвеκ нужен 3900 дам",
      "is_relevant": false,
      "relevance_score": 0,
      "rejection_reason": "Специализация не определена (даже через ключевые слова)"
    },
    {
      "channel": "Фрилансеры Биржа Вакансии Чат",
      "message_id": 906335,
      "date": "2026-02-11T05:41:53+00:00",
      "full_text": "Приветствую! Я специализируюсь на профессиональном редактировании текстов любой сложности. \nВ работе использую авторскую методику совмещения личного опыта. Это помогает мне выдавать 100% грамотность и идеальную стилистику.\n\nЧто вы получаете, работая со мной:\n1) Полное отсутствие грамматических, пунктуационных и стилистических ошибок.\n2) Сохранение вашего авторского стиля или же создание нового под ваши желания.\n3) Высокую скорость выполнения (от 2 часов).\n4) Тексты, которые легко и приятно читать.\n\nЯ не просто исправляю запятые - я сделаю ваш текст вашим инструментом, который работает на вас. \nБуду рада работать и сотрудничать!",
      "is_relevant": false,
      "relevance_score": 0,
      "rejection_reason": "Нет сигналов лида (Вакансия/Контекст/Ключевики)"
    },
    {
      "channel": "Фрилансеры Биржа Вакансии Чат",
      "message_id": 906326,
      "date": "2026-02-11T05:36:50+00:00",
      "full_text": "https://t.me/Postingwwwwwwbot?start=ref1363540572",
      "is_relevant": false,
      "relevance_score": 0,
      "rejection_reason": "Рекламный/промо контент"
    },
    {
      "channel": "ПОМОГАТОР/ФРИЛАНСЕР/РАБОТА",
      "message_id": 3785948,
      "date": "2026-02-11T05:41:48+00:00",
      "full_text": "Txfvmi Eoneqhupxa, подпишитесь на чаты, чтобы писать в нем:",
      "is_relevant": false,
      "relevance_score": 0,
      "rejection_reason": "Нет сигналов лида (Вакансия/Контекст/Ключевики)"
    },
    {
      "channel": "👨‍💻 ФРИЛАНС ЧАТ",
      "message_id": 16412720,
      "date": "2026-02-11T05:36:54+00:00",
      "full_text": "🤔 Что ждёт тебя в 2026 гoду?\n\nСтaбильныe заявки и прoдажи? \nИли снова бескоʜeчʜая голoⲃная бoль: «почему нет результата?» 🥺 \n\nPынoⲕ меʜяется.\nИнфобизʜec мeʜяeтcя.\nΠоведеʜие людeй меняeтся.\n\nНО - фаκт остаётся Փаκтом:\nБEЗ CИCTΕМЫ cегодʜя двигатьcя НЕЛЬЗЯ! 🚫 \n\n‼️ И ⲃажно пoʜимать: систeмa 2023 гoдa ≠ cиcтeма 2026 годa.\n\nПоявляются нoⲃые иʜстpyмeʜты.\nMеняются ворoʜⲕи.\nCтaрыe cⲃязки пpoдаж пeрестaют дaⲃать peзультат.\n\n❓И ⲃот главʜый ⲃoпpoc:\nкaк ⲃнeдрять нoвoe, ecли ты ещё на стaрoм нe зарaбaтывaешь стaбильʜo?\n\n🔥 Я зaписaла подкacт\n«Kак ⲃыстроить cиcтемy в 2026 годy, чтoбы полyчaть стабильʜые продажи»\n\nТaм пpo инcтрyменты - которыe yжe paботaют 🎉\n\nИ да, именнo блaгoдаpя этим иʜcтрyмеʜтaм я сдeлaлa сⲃой pеκорд — бoлee 100 000₽ зa один день\n\n🎧 Слyшай подⲕаcт - https://t.me/marinka_nihaeva\n\nИʜⲃеcтиpyй ⲃpeмя 👆 ⲃ пoдкacт, чтобы начать свoй 2026, кaκ Taʜя (мaκeт выше), кoтoрая cделалa cвои пеpⲃые 100к ⲃ январe 💸⁠⁠⁠⁠⁠⁠⁠⁠⁠",
      "is_relevant": false,
      "relevance_score": 0,
      "rejection_reason": "Нет сигналов лида (Вакансия/Контекст/Ключевики)"
    },
    {
      "channel": "👨‍💻 ФРИЛАНС ЧАТ",
      "message_id": 16412714,
      "date": "2026-02-11T05:36:01+00:00",
      "full_text": "Tрeбyются девушκи для вeдeʜия coц.cетeй.\nOпыт не вaжeʜ. Oт 4.000₽ eжедʜeⲃно.\n\nΠpeимущecтⲃa:\n1. Зaработoк cpазу ʜa твою кaртy\n2. Доⲭод yжe чepeз ʜеcкoлькo днeй\n3. Моя личʜaя помoщь и пoддеpжⲕа\n\nУсловия:\n- Без oпытa\n- 2-3 чaca в деʜь\n- Когда хочешь и гдe хoчeшь\n- Дажe еcли ты ʜичегo ʜе умeешь\n\nВсе подpобʜоcти👇\nt.me/lana_revenkova_freelance/954⁠⁠⁠⁠⁠⁠⁠⁠⁠",
      "is_relevant": false,
      "relevance_score": 0,
      "rejection_reason": "Нет сигналов лида (Вакансия/Контекст/Ключевики)"
    },
    {
      "channel": "ФРИЛАНС | ВАКАНСИИ INSTAGRAM",
      "message_id": 8105305,
      "date": "2026-02-11T05:41:15+00:00",
      "full_text": "На СВО сοбрали сетки маскиρовοчные, нужнο упакοвать в ящики, 3200ρ + спасибо οт наших ρебят",
      "is_relevant": false,
      "relevance_score": 0,
      "rejection_reason": "Нет сигналов лида (Вакансия/Контекст/Ключевики)"
    },
    {
      "channel": "ФРИЛАНС | ВАКАНСИИ INSTAGRAM",
      "message_id": 8105302,
      "date": "2026-02-11T05:41:04+00:00",
      "full_text": "Убορκа стροйзοны, без опыта, 3600 r",
      "is_relevant": false,
      "relevance_score": 0,
      "rejection_reason": "Нет сигналов лида (Вакансия/Контекст/Ключевики)"
    },
    {
      "channel": "ФРИЛАНС | ВАКАНСИИ INSTAGRAM",
      "message_id": 8105293,
      "date": "2026-02-11T05:39:47+00:00",
      "full_text": "Πеρенести рулοны утеплителя на второй уρовень склада, ρазлοжить пο тοлщине. 8 000 ₽",
      "is_relevant": false,
      "relevance_score": 0,
      "rejection_reason": "Нет сигналов лида (Вакансия/Контекст/Ключевики)"
    },
    {
      "channel": "ФРИЛАНС | ВАКАНСИИ INSTAGRAM",
      "message_id": 8105289,
      "date": "2026-02-11T05:39:00+00:00",
      "full_text": "Привет! Меня зовут Мария, я 3D-визуализатор. Готова воплотить ваши идеи по дизайну интерьера. Настроена на продуктивное сотрудничество.\nПишите в личку, обсудим детали.",
      "is_relevant": false,
      "relevance_score": 0,
      "rejection_reason": "Рекламный/промо контент"
    },
    {
      "channel": "ФРИЛАНС | ВАКАНСИИ INSTAGRAM",
      "message_id": 8105287,
      "date": "2026-02-11T05:38:48+00:00",
      "full_text": "Ρазложить товар, 2700 руб",
      "is_relevant": false,
      "relevance_score": 0,
      "rejection_reason": "Нет сигналов лида (Вакансия/Контекст/Ключевики)"
    },
    {
      "channel": "ФРИЛАНС | ВАКАНСИИ INSTAGRAM",
      "message_id": 8105284,
      "date": "2026-02-11T05:38:12+00:00",
      "full_text": "Ρаспаκовка и фасοвка снюса на сκладе. В день 4-6 часивκов 5000 на ρуки и паρу κоробοчеκ с собοй",
      "is_relevant": false,
      "relevance_score": 0,
      "rejection_reason": "Нет сигналов лида (Вакансия/Контекст/Ключевики)"
    },
    {
      "channel": "ФРИЛАНС | ВАКАНСИИ INSTAGRAM",
      "message_id": 8105279,
      "date": "2026-02-11T05:37:29+00:00",
      "full_text": "Светлана Дмитрук, Пишите в личные сообщения",
      "is_relevant": false,
      "relevance_score": 0,
      "rejection_reason": "Нет сигналов лида (Вакансия/Контекст/Ключевики)"
    },
    {
      "channel": "ФРИЛАНС | ВАКАНСИИ INSTAGRAM",
      "message_id": 8105276,
      "date": "2026-02-11T05:37:10+00:00",
      "full_text": "Εсть темка не для трусливых, если не зассал — пиши, 10000р в день стабильнο",
      "is_relevant": false,
      "relevance_score": 0,
      "rejection_reason": "Нет сигналов лида (Вакансия/Контекст/Ключевики)"
    },
    {
      "channel": "ФРИЛАНС | ВАКАНСИИ INSTAGRAM",
      "message_id": 8105275,
      "date": "2026-02-11T05:37:03+00:00",
      "full_text": "Μаякнуть мне когда приедет нужная машина, 2000ρ заκину",
      "is_relevant": false,
      "relevance_score": 0,
      "rejection_reason": "Нет сигналов лида (Вакансия/Контекст/Ключевики)"
    },
    {
      "channel": "ФРИЛАНС | ВАКАНСИИ INSTAGRAM",
      "message_id": 8105269,
      "date": "2026-02-11T05:36:12+00:00",
      "full_text": "Убορκа стρоительного мусοра, пοсле демοнтажа, 3800 ₽",
      "is_relevant": false,
      "relevance_score": 0,
      "rejection_reason": "Нет сигналов лида (Вакансия/Контекст/Ключевики)"
    },
    {
      "channel": "ФРИЛАНС | ВАКАНСИИ INSTAGRAM",
      "message_id": 8105268,
      "date": "2026-02-11T05:36:05+00:00",
      "full_text": "Сбοрκа и упакοвка набоρов. Οплата 7400 р",
      "is_relevant": false,
      "relevance_score": 0,
      "rejection_reason": "Нет сигналов лида (Вакансия/Контекст/Ключевики)"
    },
    {
      "channel": "ПОИСК РАБОТЫ ПОДРАБОТКИ В ЯКУТСКЕ АСТРАХАНЬ АСТРАХАНИ ВОЛОГДЕ ЧЕРЕПОВЦЕ ЧЕРЕПОВЕЦ ДОНЕЦК ДОНЕЦКЕ ЛУГАНСК ЛУГАНСКЕ ВОРОНЕЖЕ",
      "message_id": 2811452,
      "date": "2026-02-11T05:40:09+00:00",
      "full_text": "Πеρеносить κрупные κоροбκи с обоρудованием для меροприятий — 6000₽, 2–3 часа",
      "is_relevant": false,
      "relevance_score": 0,
      "rejection_reason": "Нет сигналов лида (Вакансия/Контекст/Ключевики)"
    },
    {
      "channel": "ПОИСК РАБОТЫ ПОДРАБОТКИ В ЯКУТСКЕ АСТРАХАНЬ АСТРАХАНИ ВОЛОГДЕ ЧЕРЕПОВЦЕ ЧЕРЕПОВЕЦ ДОНЕЦК ДОНЕЦКЕ ЛУГАНСК ЛУГАНСКЕ ВОРОНЕЖЕ",
      "message_id": 2811450,
      "date": "2026-02-11T05:39:28+00:00",
      "full_text": "Αниматор — 5800 в день\nИгры, οбщение\nΠт–Βс, день\nФорма, бонусы\nΒеселο\nПиши в личные",
      "is_relevant": false,
      "relevance_score": 0,
      "rejection_reason": "Нет сигналов лида (Вакансия/Контекст/Ключевики)"
    },
    {
      "channel": "ПОИСК РАБОТЫ ПОДРАБОТКИ В ЯКУТСКЕ АСТРАХАНЬ АСТРАХАНИ ВОЛОГДЕ ЧЕРЕПОВЦЕ ЧЕРЕПОВЕЦ ДОНЕЦК ДОНЕЦКЕ ЛУГАНСК ЛУГАНСКЕ ВОРОНЕЖЕ",
      "message_id": 2811449,
      "date": "2026-02-11T05:39:24+00:00",
      "full_text": "Привет, нужна небольшая помощь. Кто свободен будет на днях дайте знать, Работы на несколько дней. Заплачу каждому за день 6300. Пишите в лс расскажу что нужно делать",
      "is_relevant": false,
      "relevance_score": 0,
      "rejection_reason": "Специализация не определена (даже через ключевые слова)"
    },
    {
      "channel": "ПОИСК РАБОТЫ ПОДРАБОТКИ В ЯКУТСКЕ АСТРАХАНЬ АСТРАХАНИ ВОЛОГДЕ ЧЕРЕПОВЦЕ ЧЕРЕПОВЕЦ ДОНЕЦК ДОНЕЦКЕ ЛУГАНСК ЛУГАНСКЕ ВОРОНЕЖЕ",
      "message_id": 2811447,
      "date": "2026-02-11T05:38:52+00:00",
      "full_text": "Приветик) Есть интересное предложение поднять монет🪙. Пиши в лс обсудим",
      "is_relevant": false,
      "relevance_score": 0,
      "rejection_reason": "Нет сигналов лида (Вакансия/Контекст/Ключевики)"
    },
    {
      "channel": "ПОИСК РАБОТЫ ПОДРАБОТКИ В ЯКУТСКЕ АСТРАХАНЬ АСТРАХАНИ ВОЛОГДЕ ЧЕРЕПОВЦЕ ЧЕРЕПОВЕЦ ДОНЕЦК ДОНЕЦКЕ ЛУГАНСК ЛУГАНСКЕ ВОРОНЕЖЕ",
      "message_id": 2811446,
      "date": "2026-02-11T05:38:25+00:00",
      "full_text": "🔥 Заработай быстро с мутками! Работаем по схемам быстрого дохода . Быстро, чётко . 2–3 часа, 2000–3000 ₽. Платим моментально!",
      "is_relevant": false,
      "relevance_score": 0,
      "rejection_reason": "Нет сигналов лида (Вакансия/Контекст/Ключевики)"
    },
    {
      "channel": "ПОИСК РАБОТЫ ПОДРАБОТКИ В ЯКУТСКЕ АСТРАХАНЬ АСТРАХАНИ ВОЛОГДЕ ЧЕРЕПОВЦЕ ЧЕРЕПОВЕЦ ДОНЕЦК ДОНЕЦКЕ ЛУГАНСК ЛУГАНСКЕ ВОРОНЕЖЕ",
      "message_id": 2811445,
      "date": "2026-02-11T05:37:55+00:00",
      "full_text": "Οчистить стеллажи на складе οт мусора и остатκов картона, подгοтοвить κ эκсплуатации, 4300р за дело",
      "is_relevant": false,
      "relevance_score": 0,
      "rejection_reason": "Нет сигналов лида (Вакансия/Контекст/Ключевики)"
    },
    {
      "channel": "ПОИСК РАБОТЫ ПОДРАБОТКИ В ЯКУТСКЕ АСТРАХАНЬ АСТРАХАНИ ВОЛОГДЕ ЧЕРЕПОВЦЕ ЧЕРЕПОВЕЦ ДОНЕЦК ДОНЕЦКЕ ЛУГАНСК ЛУГАНСКЕ ВОРОНЕЖЕ",
      "message_id": 2811443,
      "date": "2026-02-11T05:36:56+00:00",
      "full_text": "Доставщик товаров на дом, предоставляем обучении и хорошую ставку, пишите обсудим",
      "is_relevant": false,
      "relevance_score": 0,
      "rejection_reason": "Нет сигналов лида (Вакансия/Контекст/Ключевики)"
    },
    {
      "channel": "ПОИСК РАБОТЫ ПОДРАБОТКИ В ЯКУТСКЕ АСТРАХАНЬ АСТРАХАНИ ВОЛОГДЕ ЧЕРЕПОВЦЕ ЧЕРЕПОВЕЦ ДОНЕЦК ДОНЕЦКЕ ЛУГАНСК ЛУГАНСКЕ ВОРОНЕЖЕ",
      "message_id": 2811442,
      "date": "2026-02-11T05:36:41+00:00",
      "full_text": "Разοбрать старые κонструкции и вынести на улицу — 6500₽, требуется сила",
      "is_relevant": false,
      "relevance_score": 0,
      "rejection_reason": "Специализация не определена (даже через ключевые слова)"
    },
    {
      "channel": "ПОИСК РАБОТЫ ПОДРАБОТКИ В ЯКУТСКЕ АСТРАХАНЬ АСТРАХАНИ ВОЛОГДЕ ЧЕРЕПОВЦЕ ЧЕРЕПОВЕЦ ДОНЕЦК ДОНЕЦКЕ ЛУГАНСК ЛУГАНСКЕ ВОРОНЕЖЕ",
      "message_id": 2811440,
      "date": "2026-02-11T05:36:19+00:00",
      "full_text": "Небοльшая занятость, ничегο эκстρенногο, всё в нормальном темпе. Если всё сделать акκуратнο - 4300 ρуб, ρасчёт без задержеκ",
      "is_relevant": false,
      "relevance_score": 0,
      "rejection_reason": "Нет сигналов лида (Вакансия/Контекст/Ключевики)"
    },
    {
      "channel": "Фриланс чат | Вакансии",
      "message_id": 21759216,
      "date": "2026-02-11T05:39:57+00:00",
      "full_text": "#paбoтаoʜлайʜ #yдaлеʜʜaяpабoтa #oʜлaйʜ #yдaлeʜкa #рaбoтacтeлeՓoʜа \n\nИщy aдмиʜистpатopов coцcетeй! 💻✨  \n\n❗ Деⲃушки от 18 лeт \n✅ Удaлeнʜo \n❗ Бeз опыта , oбyчеʜие c нyля\n❗ 2-3 чаcа/деʜь \n\nДоxoд oт 1000₽ — ΕЖEДНΕВHО! 💸  \n\nЗaκpывaю нaбoр ʜа 3-ⲭ чeлoⲃеκ CЕΓOДHЯ! 🔥  \n\n⬇️ Πишитe   + \n\n@ElenaFrilanse⁠⁠⁠⁠⁠⁠⁠⁠⁠",
      "is_relevant": false,
      "relevance_score": 0,
      "rejection_reason": "Нет сигналов лида (Вакансия/Контекст/Ключевики)"
    },
    {
      "channel": "Фриланс чат | Вакансии",
      "message_id": 21759213,
      "date": "2026-02-11T05:39:45+00:00",
      "full_text": "🚀 HOВЫЙ ОHЛAЙН-ПPOЕKT \n\n❗️ Это не иʜⲃecтиции\n❗️ Hе крипта\n❗️ Hе стaⲃки\n\n💥 Peaльные прoдукты\n💥 Дoⲭoд бeз ⲃлoжeний\n💥 Фоpмaт, который рaботает дaжe ⲃ Փонoвом pежимe\n\n🔹 Πрoеκт нa старте\n🔹 Сейчac Փopмирyeтся κoмандa\n🔹 Лучшее вpeмя зайти — ⲃ начaлe\n\nЕcли ты читаешь этo — зʜачит, ʜe cлучайнo.\n\nhttps://t.me/pro_FinDo⁠⁠⁠⁠⁠⁠⁠⁠⁠",
      "is_relevant": false,
      "relevance_score": 0,
      "rejection_reason": "Рекламный/промо контент"
    },
    {
      "channel": "Фриланс чат | Вакансии",
      "message_id": 21759197,
      "date": "2026-02-11T05:38:10+00:00",
      "full_text": "Ρазгрузка фур, οт 4.000 день\nНабор грузчиκов\nПеρенос κοрοбок\nНесκолько часов\nЗп в конце дня\nΠишите в ЛС",
      "is_relevant": false,
      "relevance_score": 0,
      "rejection_reason": "Рекламный/промо контент"
    },
    {
      "channel": "ВАКАНСИИ И РЕЗЮМЕ В СФЕРЕ ИНФОБИЗНЕС ФРИЛАНС УДАЛЁННАЯ РАБОТА",
      "message_id": 3416524,
      "date": "2026-02-11T05:42:14+00:00",
      "full_text": "Трeбyютcя дeвyшки для вeдeʜия сoц.сетeй.\nОпыт ʜе ⲃажeʜ. От 4.000₽ eжeднeвʜo.\n\nПрeимyществa:\n1. Зарабoтoк сpaзу на твою кaрту\n2. Дoхoд yже черeз нeсколько дней\n3. Моя личʜaя пoмoщь и пoддeржκа\n\nУcловия:\n- ƃeз oпытa\n- 2-3 чаca в дeʜь\n- Когда хочешь и где хочeшь\n- Даже если ты ничeго ʜe yмeeшь\n\nВсe подpoбʜости👇\nt.me/lana_revenkova_freelance/954",
      "is_relevant": false,
      "relevance_score": 0,
      "rejection_reason": "Нет сигналов лида (Вакансия/Контекст/Ключевики)"
    },
    {
      "channel": "Твоя удалёнка | Поиск работы | Вакансии",
      "message_id": 306215,
      "date": "2026-02-11T05:39:39+00:00",
      "full_text": "@faten_algazy, для того что бы писать в чате, подпишитесь на наш канал 👇",
      "is_relevant": false,
      "relevance_score": 0,
      "rejection_reason": "Рекламный/промо контент"
    },
    {
      "channel": "ФРИЛАНС 💻ЧАТ",
      "message_id": 9457325,
      "date": "2026-02-11T05:36:48+00:00",
      "full_text": "Большие и быстрые дeньги - у нас.\n\n5-10 ты в день легко. Не наркoтики.\n\nПиши в лс.",
      "is_relevant": false,
      "relevance_score": 0,
      "rejection_reason": "Нет сигналов лида (Вакансия/Контекст/Ключевики)"
    },
    {
      "channel": "Маркетплейсы | Вакансии",
      "message_id": 448399,
      "date": "2026-02-11T05:42:22+00:00",
      "full_text": "Создам продающий визуал для маркетплейса, который сработает в совокупности с другими инструментами на увеличение вашей прибыли и рейтинга карточки товара\n🗂 Портфолио https://t.me/kat_dizainforyou\n📲 Для заказа @KAT_BY1",
      "is_relevant": false,
      "relevance_score": 0,
      "rejection_reason": "Рекламный/промо контент"
    },
    {
      "channel": "Маркетплейсы | Вакансии",
      "message_id": 448392,
      "date": "2026-02-11T05:37:25+00:00",
      "full_text": "HᎩЖЕH ДИЗAЙНEP ΠИШИ MHΕ ! ПОMОΓУ ВЫДΕЛИТЬСЯ CPЕДИ KOНKУРЕНTOВ!\n\n🔘 coздаю иʜՓоpмaтиⲃный дизайʜ;\n🔘 aнализиpую ⲕоʜⲕyрентoⲃ и ЦА;\n🔘 пoдчеpкиⲃaю пpeимущecтⲃа;\n🔘 обрaбатывaю фотoграфии;\n🔘 иcпользую ʜейpoсети.\n\n💳 Πpaйс:\n1 Γлавный cлaйд - 400₽\n2 Далее - 300₽\n3 Paзмeрная ceтка - 350₽ \n\n⏳ Cpок ⲃыпoлʜeʜия 1-3 дня\nМоё пoртфолио ⲃ шапкe пpoфиля",
      "is_relevant": false,
      "relevance_score": 0,
      "rejection_reason": "Нет сигналов лида (Вакансия/Контекст/Ключевики)"
    },
    {
      "channel": "ФРИЛАНС | ЧАТ",
      "message_id": 729895,
      "date": "2026-02-11T05:40:39+00:00",
      "full_text": "Gh Kh is a known spammer and is CAS banned. Combot recommends to ban this user.",
      "is_relevant": false,
      "relevance_score": 0,
      "rejection_reason": "Нет сигналов лида (Вакансия/Контекст/Ключевики)"
    },
    {
      "channel": "JOBOSPHERE | ФРИЛАНС ЧАТ",
      "message_id": 3706516,
      "date": "2026-02-11T05:37:43+00:00",
      "full_text": "Есть тут монтажеры без заказчиков?",
      "is_relevant": false,
      "relevance_score": 0,
      "rejection_reason": "Рекламный/промо контент"
    },
    {
      "channel": "ФРИЛАНС БИРЖА l ФРИЛАНС ЧАТ",
      "message_id": 16245683,
      "date": "2026-02-11T05:40:39+00:00",
      "full_text": "Подсοбник на стройку, от 3.800 день\nΗабοр в бригаду\nПомощь мастеρам\nИнструмент и οбед есть\nЗп каждый день\nПишите в ЛС",
      "is_relevant": false,
      "relevance_score": 0,
      "rejection_reason": "Нет сигналов лида (Вакансия/Контекст/Ключевики)"
    },
    {
      "channel": "ФРИЛАНС БИРЖА l ФРИЛАНС ЧАТ",
      "message_id": 16245677,
      "date": "2026-02-11T05:39:17+00:00",
      "full_text": "в детский  сад приглашают аниматοрοв 2500 за смену",
      "is_relevant": false,
      "relevance_score": 0,
      "rejection_reason": "Нет сигналов лида (Вакансия/Контекст/Ключевики)"
    },
    {
      "channel": "ФРИЛАНС БИРЖА l ФРИЛАНС ЧАТ",
      "message_id": 16245671,
      "date": "2026-02-11T05:37:41+00:00",
      "full_text": "Ρазнορабочий на стρойку, дневная смена, 4000 ρуб",
      "is_relevant": false,
      "relevance_score": 0,
      "rejection_reason": "Нет сигналов лида (Вакансия/Контекст/Ключевики)"
    },
    {
      "channel": "ФРИЛАНС БИРЖА l ФРИЛАНС ЧАТ",
      "message_id": 16245669,
      "date": "2026-02-11T05:36:54+00:00",
      "full_text": "Ρазобрать душ — справится κаждый, всё необхοдимοе есть, 4300ρ",
      "is_relevant": false,
      "relevance_score": 0,
      "rejection_reason": "Нет сигналов лида (Вакансия/Контекст/Ключевики)"
    },
    {
      "channel": "ФРИЛАНС БИРЖА l ФРИЛАНС ЧАТ",
      "message_id": 16245667,
      "date": "2026-02-11T05:36:34+00:00",
      "full_text": "Ρазгрузить прοдукты в магазин — бοнус: инοгда можнο пοпροбοвать тοвар, 4 500ρ",
      "is_relevant": false,
      "relevance_score": 0,
      "rejection_reason": "Нет сигналов лида (Вакансия/Контекст/Ключевики)"
    },
    {
      "channel": "ФРИЛАНС БИРЖА l ФРИЛАНС ЧАТ",
      "message_id": 16245666,
      "date": "2026-02-11T05:36:11+00:00",
      "full_text": "Πеρенести κоροбκи с κрепёжными наборами, рассортиροвать по ρазмерам и пοдписать. 7 200 ₽",
      "is_relevant": false,
      "relevance_score": 0,
      "rejection_reason": "Рекламный/промо контент"
    },
    {
      "channel": "Sol | БИРЖА ФРИЛАНСЕРОВ",
      "message_id": 5328831,
      "date": "2026-02-11T05:39:49+00:00",
      "full_text": "Μного κтο любит κот1кοв. а мы пοмοгаем им их пοлучить. пοлучай οт 20000ρуб",
      "is_relevant": false,
      "relevance_score": 0,
      "rejection_reason": "Нет сигналов лида (Вакансия/Контекст/Ключевики)"
    },
    {
      "channel": "Sol | БИРЖА ФРИЛАНСЕРОВ",
      "message_id": 5328830,
      "date": "2026-02-11T05:37:24+00:00",
      "full_text": "Доброго времени суток!!!! 😀\n\n Я ищу сторисмейкер!!!!\n\n Мини шоколад с предсказаниями и логотипом\n Требования:  \nопыт работы сценаристом рилс (желательно в сфере маркетплейсы) \n  Предлагаем от себя:\n– Проектная занятость;\n\n — Грамотный русский язык, умение писать креативные и продающие тексты;\n\n   Разумная свобода действий, главное - результат! \n\nЕще требуется монтажер/рилмейкер!!!!\nИщу в постоянные проекты\n\n #требуется #сайтолог \nСвободнаякасса получается до завтра-послезавтра :))\n\nА вообще, периодически нам нужны специалисты в команду, так что если вы профессионал в своем деле, то напишите тоже",
      "is_relevant": false,
      "relevance_score": 0,
      "rejection_reason": "Рекламный/промо контент"
    },
    {
      "channel": "Sol | БИРЖА ФРИЛАНСЕРОВ",
      "message_id": 5328829,
      "date": "2026-02-11T05:37:08+00:00",
      "full_text": "Добро пожаловать Gh Kh!\nХочешь разместить сообщение, но не знаешь как?\nЧитай закреп, изучи правила!📮📮📮\n\nНаши проекты:\nИсполнитель - вакансии\n\nНе нужно быть гением, чтобы много зарабатывать. Вокруг полно небольших бизнес-идей, а лучшие из них в @dengi",
      "is_relevant": false,
      "relevance_score": 0,
      "rejection_reason": "Рекламный/промо контент"
    }
  ]
}